{"assets/bg/bonus_game_page.png":["assets/bg/bonus_game_page.png"],"assets/bg/choose_game_page.png":["assets/bg/choose_game_page.png"],"assets/bg/loading_page.png":["assets/bg/loading_page.png"],"assets/bg/loading_page_cloud.png":["assets/bg/loading_page_cloud.png"],"assets/bg/loading_page_pers.png":["assets/bg/loading_page_pers.png"],"assets/bg/main_page.png":["assets/bg/main_page.png"],"assets/bg/settings_page.png":["assets/bg/settings_page.png"],"assets/bg/start_game_page.png":["assets/bg/start_game_page.png"],"assets/icons/btn_about.png":["assets/icons/btn_about.png"],"assets/icons/btn_arrow_back.png":["assets/icons/btn_arrow_back.png"],"assets/icons/btn_bonus_game.png":["assets/icons/btn_bonus_game.png"],"assets/icons/btn_bottom_play.png":["assets/icons/btn_bottom_play.png"],"assets/icons/btn_choose_5.png":["assets/icons/btn_choose_5.png"],"assets/icons/btn_choose_6.png":["assets/icons/btn_choose_6.png"],"assets/icons/btn_choose_7.png":["assets/icons/btn_choose_7.png"],"assets/icons/btn_choose_8.png":["assets/icons/btn_choose_8.png"],"assets/icons/btn_play.png":["assets/icons/btn_play.png"],"assets/icons/btn_settings.png":["assets/icons/btn_settings.png"],"assets/icons/level_index.png":["assets/icons/level_index.png"],"assets/images/active_level.png":["assets/images/active_level.png"],"assets/images/bg_pause.png":["assets/images/bg_pause.png"],"assets/images/bonus_bg.png":["assets/images/bonus_bg.png"],"assets/images/book.png":["assets/images/book.png"],"assets/images/btt.png":["assets/images/btt.png"],"assets/images/card1.png":["assets/images/card1.png"],"assets/images/card2.png":["assets/images/card2.png"],"assets/images/card3.png":["assets/images/card3.png"],"assets/images/card4.png":["assets/images/card4.png"],"assets/images/card5.png":["assets/images/card5.png"],"assets/images/card6.png":["assets/images/card6.png"],"assets/images/card7.png":["assets/images/card7.png"],"assets/images/card8.png":["assets/images/card8.png"],"assets/images/cardx.png":["assets/images/cardx.png"],"assets/images/coins.png":["assets/images/coins.png"],"assets/images/continue.png":["assets/images/continue.png"],"assets/images/difficulty.png":["assets/images/difficulty.png"],"assets/images/in_active_level.png":["assets/images/in_active_level.png"],"assets/images/pause.png":["assets/images/pause.png"],"assets/images/price.png":["assets/images/price.png"],"assets/images/quit.png":["assets/images/quit.png"],"assets/images/random.png":["assets/images/random.png"],"assets/images/settings.png":["assets/images/settings.png"],"assets/images/textLose.png":["assets/images/textLose.png"],"assets/images/textWin.png":["assets/images/textWin.png"],"assets/images/timer.png":["assets/images/timer.png"],"assets/music/complete_word.mp3":["assets/music/complete_word.mp3"],"assets/music/end_level.mp3":["assets/music/end_level.mp3"],"assets/music/time_out.mp3":["assets/music/time_out.mp3"],"assets/music/wrong_word.mp3":["assets/music/wrong_word.mp3"],"packages/cupertino_icons/assets/CupertinoIcons.ttf":["packages/cupertino_icons/assets/CupertinoIcons.ttf"]}